COPYING
MANIFEST.in
README.md
setup.py
Cydra.egg-info/PKG-INFO
Cydra.egg-info/SOURCES.txt
Cydra.egg-info/dependency_links.txt
Cydra.egg-info/entry_points.txt
Cydra.egg-info/not-zip-safe
Cydra.egg-info/requires.txt
Cydra.egg-info/top_level.txt
cydra/__init__.py
cydra/cli.py
cydra/component.py
cydra/error.py
cydra/loader.py
cydra/project.py
cydra/util.py
cydra/caching/__init__.py
cydra/caching/subject.py
cydra/config/__init__.py
cydra/config/file.py
cydra/datasource/__init__.py
cydra/datasource/file.py
cydra/datasource/mongo.py
cydra/permission/__init__.py
cydra/permission/htpasswd.py
cydra/repository/__init__.py
cydra/repository/git.py
cydra/repository/hg.py
cydra/repository/svn.py
cydra/repository/scripts/git_post-receive.sh
cydra/repository/scripts/hg_commit.sh
cydra/repository/scripts/svn_commit.sh
cydra/web/__init__.py
cydra/web/debugging.py
cydra/web/filters.py
cydra/web/themes.py
cydra/web/wsgihelper.py
cydra/web/frontend/__init__.py
cydra/web/frontend/hooks.py
cydra/web/frontend/templates/frontend_base.jhtml
cydra/web/frontend/templates/index.jhtml
cydra/web/frontend/templates/project.jhtml
cydra/web/frontend/templates/userhome.jhtml
cydra/web/frontend/templates/usersettings.jhtml
cydra/web/frontend/templates/util.jhtml
cydra/web/static/jquery-rest-shortcuts.js
cydra/web/static/jquery-ui-overrides.css
cydra/web/static/jquery-ui.js
cydra/web/static/jquery.dotimeout.js
cydra/web/static/jquery.js
cydra/web/static/style.css
cydra/web/static/jquery-ui-smoothness/style.css
cydra/web/static/jquery-ui-smoothness/images/ui-bg_flat_0_aaaaaa_40x100.png
cydra/web/static/jquery-ui-smoothness/images/ui-bg_flat_75_ffffff_40x100.png
cydra/web/static/jquery-ui-smoothness/images/ui-bg_glass_55_fbf9ee_1x400.png
cydra/web/static/jquery-ui-smoothness/images/ui-bg_glass_65_ffffff_1x400.png
cydra/web/static/jquery-ui-smoothness/images/ui-bg_glass_75_dadada_1x400.png
cydra/web/static/jquery-ui-smoothness/images/ui-bg_glass_75_e6e6e6_1x400.png
cydra/web/static/jquery-ui-smoothness/images/ui-bg_glass_95_fef1ec_1x400.png
cydra/web/static/jquery-ui-smoothness/images/ui-bg_highlight-soft_75_cccccc_1x100.png
cydra/web/static/jquery-ui-smoothness/images/ui-icons_222222_256x240.png
