Metadata-Version: 1.1
Name: Cydra
Version: 0.2
Summary: Code hosting platform
Home-page: http://www.cydra.org
Author: Manuel Stocker
Author-email: mensi@mensi.ch
License: GPL
Platform: UNKNOWN
Classifier: Development Status :: 2 - Pre-Alpha
Classifier: Environment :: Web Environment
Classifier: Intended Audience :: Developers
Classifier: License :: OSI Approved :: GNU General Public License (GPL)
Classifier: Operating System :: OS Independent
Classifier: Programming Language :: Python
